bhoonidhi_downloader/__init__.py
bhoonidhi_downloader/__main__.py
bhoonidhi_downloader/authenticate.py
bhoonidhi_downloader/cart_actions.py
bhoonidhi_downloader/constants.py
bhoonidhi_downloader/scene_search.py
bhoonidhi_downloader/utils.py
bhoonidhi_downloader-0.1.21.dist-info/METADATA
bhoonidhi_downloader-0.1.21.dist-info/WHEEL
bhoonidhi_downloader-0.1.21.dist-info/entry_points.txt
bhoonidhi_downloader-0.1.21.dist-info/RECORD
