Metadata-Version: 2.3
Name: bhoonidhi-downloader
Version: 0.1.21
Summary: Command line tool for searching and downloading satellite data from Bhoonidhi
Project-URL: Repository, https://github.com/geovicco-dev/bhoonidhi-downloader
Author-email: geovicco-dev <geovicco.dev@gmail.com>
License-Expression: MIT
Requires-Python: >=3.8
Requires-Dist: geopandas==1.0.1
Requires-Dist: requests>=2.32.3
Requires-Dist: tabulate>=0.9.0
Requires-Dist: tqdm>=4.66.4
Requires-Dist: typer>=0.12.3
Requires-Dist: wget>=3.2
